{
  "name": "Essie Moran",
  "age": 55,
  "address": {
    "street": "Borkon Manor",
    "city": "Waphihu",
    "state": "OK",
    "zip": "68520"
  },
  "contact": {
    "phone": "(962) 285-5418",
    "servicePhone": "800896451"
  },
  "birthday": "1964-03-26T16:29:49.531Z",
  "ip": "164.111.202.145",
  "foo": "bar",
  "profile": {
    "about": "Ujhukmif owgob tu edega osirufob notkactur mo wed zafuluv abalege jasibin cike kolvod foacu citeva. Zojmen umivivis raabecug bodigihi obibe larja mevgozi teunula izgefu soetja tothafe darnihu tid ajpamgo lu mijokipo pozhene. Isubovec picir uzfifwig zuil amikuw ojivin inabopiso mor ve cakajon uka ozorag satama avopod vaeju. Wo puruw ofisiwnoc tigad meihu gumtag wimukon madok loub dahpupjim ceriva gobdahhij. Dulcirmu gar ge coaj bob wuf zi wa da jipenu ehimjet juvmokir ikfawo ganwuh koamo us.",
    "bio": "Codgu cikpa uba caut megediw iduikfat rap te awo zese odamiz po za gut rohlorub fu gelooz. Zapji hofa hi ef decaaza gegge kefur rotunin mihisec gurafso ziczu malor. Urokot otafuwres basoc mam pakwuen ubjuane wono zohhouc go nagez ohi ub izope ohbo. Oroleve wareoso sojjas pun paeghu peap wuheblu ibci he uto likdopgu kipohne im sevune."
  },
  "apiKey": "bc990331b7c8c6371da83d477265a7a05da56ade2c9d3886edf82a7950e120f0",
  "currency": {
    "code": "MYR",
    "name": "Malaysia Ringgit"
  }
}