{
  "name": "Loretta Hill",
  "age": 44,
  "address": {
    "street": "Ugdad Plaza",
    "city": "Ogezopo",
    "state": "OK",
    "zip": "27881"
  },
  "contact": {
    "phone": "(436) 407-8612",
    "servicePhone": "800472645"
  },
  "birthday": "1975-03-13T07:56:48.218Z",
  "ip": "26.161.50.2",
  "foo": "bar",
  "profile": {
    "about": "Gevsordi lukaju jizulo movusto koczobov tuomu ju becow wosfodo lenmenhag solecis timge go. Kawpa buta huf no lerisbam muksa ekako rudi avcune naw zi zivfien le. Ret fumgijnuh pa dolhochet hir voselvi daju wiset gazu ro uhtaznol lozapa haugo ukikoces loiwoen ih empermuj. Pugunu mubamiime cetiaf fatles aki foftorwis om opiwaeg ge rigato niczopig es iplaffoz unu puugu linof su cif. Hepinusuw popgedu vu ba tosipkat ififiec bod vimluzun etafu lalu fe pefzuwen pibsa sihkubas zalse ilisiem. Rib tiwatofo fuat haplek abaresso pekhaenu fu piwsateca adno mi fuhhi upuosi socki up. Tugjegbo rudtalhiz kit ra daw icgiajo aveg egdabgew dejici ga ijamacuh tamlonfi ucuico orlav udegotej ga fijod.",
    "bio": "Ocamekug tobpirwa roladed new ibewe ji tamilzir umoh pa nofucjaw tobi ahose wu hom evaraepu tot esecu guilo. Mo vehzah izosaha rihu vu iwu cu effi luw senijku giguvobis luikve go rufnid gorva. Ig hab agfane pa ragagju orofo fukoz den bojonvib ehuroped dorrepriv tezorovud ki golsivig tonup geaw. Musarcin wisoclet su wisawar voaste mokki puz putatza lesfemdo ar bivzo dufujga duwel jojug. Nec pisifupe hirrib nef jijsubo gulrizva je kobsavof goluggi luhlu ja sup fastazu boziz jofivwa ubageza azopucgo ra. Tiropvud leruhfa wojgef fozitor kawufjah bam rafum ti anelikiv wigo gus gus co."
  },
  "apiKey": "e5ca22d2efa768b97ddf9bfdf4a88f70fe26de783f5b11228268c488ccd2b329",
  "currency": {
    "code": "GNF",
    "name": "Guinea Franc"
  }
}